README.md
setup.py
epic_utils/__init__.py
epic_utils/animation.py
epic_utils/config.py
epic_utils/core.py
epic_utils/debug.py
epic_utils/decorators.py
epic_utils/error.py
epic_utils/fileSys.py
epic_utils/print_tools.py
epic_utils.egg-info/PKG-INFO
epic_utils.egg-info/SOURCES.txt
epic_utils.egg-info/dependency_links.txt
epic_utils.egg-info/requires.txt
epic_utils.egg-info/top_level.txt
epic_utils/pygame/__init__.py
epic_utils/pygame/assets.py
epic_utils/pygame/config.py
epic_utils/pygame/pygameApp.py
epic_utils/pygame/pygameUI.py
epic_utils/robloxapi/__init__.py
epic_utils/robloxapi/core.py
epic_utils/robloxapi/datastore.py
epic_utils/websockets/__init__.py
epic_utils/websockets/client.py
epic_utils/websockets/server.py