Metadata-Version: 2.4
Name: epic-utils
Version: 0.3.8
Summary: Dependencies i regurlarly use
Author: Epic099
Author-email: 
Classifier: Programming Language :: Python :: 3
Classifier: License :: OSI Approved :: MIT License
Classifier: Operating System :: OS Independent
Requires-Python: >=3.6
Requires-Dist: pygame
Requires-Dist: requests
Requires-Dist: numpy
Requires-Dist: websockets
Dynamic: author
Dynamic: classifier
Dynamic: requires-dist
Dynamic: requires-python
Dynamic: summary
